{"sscData": [
    {
      "name": "Mast. Kanav J. Mandrekar",
      "perc": "93.67%",
      "img": "Kanav"
    },
    {
        "name": "Mast. Shaan K. Gadekar",
        "perc": "90.83%",
        "img": "Shaan"
      },
      {
        "name": "Mast. Veer G. Bhobe",
        "perc": "87.17%",
        "img": "Veer"
      },
      {
        "name": "Miss Prapti N. Mandrekar",
        "perc": "85.00%",
        "img": "Prapti"
      },
      {
        "name": "Miss Varada M. Hajare",
        "perc": "82.50%",
        "img": "Varada"
      },
      {
        "name": "Miss Urvi U. Ajgaokar",
        "perc": "80.50%",
        "img": "Urvi"
      },
      {
        "name": "Miss Nirjara Krishna Poojari",
        "perc": "79.00%",
        "img": "Nirjara"
      },
      {
        "name": "Mast. Shubhankar B. Salgaonkar",
        "perc": "78.33%",
        "img": "Shubhankar"
      },
      {
        "name": "Mast. Gaurav K. Kalangutkar",
        "perc": "78.00%",
        "img": "Gaurav"
      }]
}